t_python_markdown/__init__.py
t_python_markdown/t_python_markdown.py
t_python_markdown/extensions/__init__.py
t_python_markdown/extensions/mkdocs.py
t_python_markdown-1.4.1.dist-info/LICENSE
t_python_markdown-1.4.1.dist-info/METADATA
t_python_markdown-1.4.1.dist-info/WHEEL
t_python_markdown-1.4.1.dist-info/top_level.txt
t_python_markdown-1.4.1.dist-info/RECORD
