Metadata-Version: 2.1
Name: t-python-markdown
Version: 1.4.1
Summary: A simple to use markdown generator for Python.
Author-email: t-python-markdown <t-python-markdown@toyne.cix.co.uk>
Maintainer-email: t-python-markdown <t-python-markdown@toyne.cix.co.uk>
License: MIT License
Project-URL: homepage, https://www.cix.co.uk/~toyne/t-python-markdown/
Project-URL: documentation, https://www.cix.co.uk/~toyne/t-python-markdown/
Keywords: markdown
Classifier: Programming Language :: Python :: 3
Classifier: Operating System :: OS Independent
Requires-Python: >=3.7
License-File: LICENSE
Requires-Dist: PyYAML
Provides-Extra: dependencies
Requires-Dist: markdown ; extra == 'dependencies'
